beproductive/__init__.py
beproductive/__main__.py
beproductive/_nbdev.py
beproductive/beproductive.py
beproductive/blocker.py
beproductive/blocklist.py
beproductive/config.py
beproductive/pomodoro.py
beproductive-0.2.5.dist-info/LICENSE
beproductive-0.2.5.dist-info/METADATA
beproductive-0.2.5.dist-info/WHEEL
beproductive-0.2.5.dist-info/entry_points.txt
beproductive-0.2.5.dist-info/top_level.txt
beproductive-0.2.5.dist-info/RECORD
