Metadata-Version: 2.1
Name: beproductive
Version: 0.2.5
Summary: Block distracting websites and set up a Pomodoro timer. Focus on your work.
Home-page: https://github.com/johannesstutz/beproductive/tree/master/
Author: Johannes Stutz
Author-email: johannesstutz@gmail.com
License: Apache Software License 2.0
Keywords: nbdev,productivity
Platform: UNKNOWN
Classifier: Development Status :: 3 - Alpha
Classifier: Intended Audience :: Developers
Classifier: License :: OSI Approved :: Apache Software License
Classifier: Natural Language :: English
Classifier: Programming Language :: Python :: 3.6
Classifier: Programming Language :: Python :: 3.7
Classifier: Programming Language :: Python :: 3.8
Requires-Python: >=3.6
Requires-Dist: pyyaml
